{
  "user_id": "905058123084091413",
  "tag": "縦連",
  "slug": "tt",
  "fixed": true,
  "count": 4,
  "score_count": 2,
  "songs": [
    {
      "id": 2468,
      "source": "sl",
      "level": "sl0",
      "title": "Kurofune [SP another]",
      "chart_name": "",
      "display_title": "Kurofune [SP another]",
      "md5": "773cfa22720afd6be5fd3fa2ada540a5",
      "sha256": "55eb91bb840fc0be2e8805cdb219dc31f8f1af4256e115ee956db788c5fec4bb",
      "artist": "54cm",
      "songdata_title": "Kurofune",
      "songdata_subtitle": "[SP another]",
      "url": "http://manbow.nothing.sh/event/event.cgi?action=More_def&num=260&event=116",
      "memo": "",
      "tag": "縦連",
      "comment": ""
    },
    {
      "id": 3176,
      "source": "sl",
      "level": "sl3",
      "title": "Neo Side",
      "chart_name": "",
      "display_title": "Neo Side",
      "md5": "",
      "sha256": "",
      "artist": "",
      "songdata_title": "",
      "songdata_subtitle": "",
      "url": "https://manbow.nothing.sh/event/event.cgi?action=More_def&num=332&event=140",
      "memo": "",
      "tag": "縦連",
      "comment": ""
    },
    {
      "id": 4126,
      "source": "sl",
      "level": "sl10",
      "title": "Central GRAY [Crazy]",
      "chart_name": "",
      "display_title": "Central GRAY [Crazy]",
      "md5": "c16ad6046d2f0d5f65a66bbbba6aaaa8",
      "sha256": "756c5bf430dc5284695b3deaf9d9e821e3a832025f2b5f79bdad4c816f1d3795",
      "artist": "P.E. / D",
      "songdata_title": "Central GRAY [Crazy]",
      "songdata_subtitle": "",
      "url": "http://absolute.pv.land.to/uploader/src/up4378.rar",
      "memo": "",
      "tag": "縦連",
      "comment": ""
    },
    {
      "id": 420,
      "source": "st",
      "level": "st0",
      "title": "ちんこ音頭2012",
      "chart_name": "",
      "display_title": "ちんこ音頭2012",
      "md5": "",
      "sha256": "",
      "artist": "",
      "songdata_title": "",
      "songdata_subtitle": "",
      "url": "http://sagena.harisen.jp/",
      "memo": "",
      "tag": "縦連",
      "comment": ""
    }
  ]
}